serverless_devs/__init__.py
serverless_devs/__main__.py
serverless_devs/installer.py
serverless_devs-1.0.4.dist-info/licenses/LICENSE
serverless_devs-1.0.4.dist-info/METADATA
serverless_devs-1.0.4.dist-info/WHEEL
serverless_devs-1.0.4.dist-info/top_level.txt
serverless_devs-1.0.4.dist-info/RECORD
