Metadata-Version: 2.4
Name: serverless-devs
Version: 1.0.4
Summary: Serverless Devs 开发者工具 - Python 安装包（自动安装最新版本）
Home-page: https://github.com/Serverless-Devs/Serverless-Devs
Author: Serverless Devs
Author-email: Serverless Devs <service@serverless-devs.com>
License: MIT
Project-URL: Homepage, https://www.serverless-devs.com/
Project-URL: Documentation, https://www.serverless-devs.com/
Project-URL: Repository, https://github.com/Serverless-Devs/Serverless-Devs
Keywords: serverless,devs,aliyun,faas
Classifier: Development Status :: 5 - Production/Stable
Classifier: Intended Audience :: Developers
Classifier: Programming Language :: Python :: 3
Requires-Python: >=3.7
License-File: LICENSE
Dynamic: author
Dynamic: home-page
Dynamic: license-file
Dynamic: requires-python
